KUKoLex/__init__.py
KUKoLex/kukolex.py
KUKoLex/__pycache__/__init__.cpython-36.pyc
KUKoLex/__pycache__/__init__.cpython-37.pyc
KUKoLex/__pycache__/kukolex.cpython-36.pyc
KUKoLex/__pycache__/kukolex.cpython-37.pyc
KUKoLex/data/__init__.py
KUKoLex/data/chars.txt
KUKoLex/data/tags.txt
KUKoLex/data/words.txt
KUKoLex/data/kmat/_exploit/Makefile
KUKoLex/data/kmat/_exploit/b2t.c
KUKoLex/data/kmat/_exploit/bin2txt.h
KUKoLex/data/kmat/_exploit/binio.c
KUKoLex/data/kmat/_exploit/binio.h
KUKoLex/data/kmat/_exploit/dafst.c
KUKoLex/data/kmat/_exploit/dafst.h
KUKoLex/data/kmat/_exploit/file2lines.c
KUKoLex/data/kmat/_exploit/fst_get_probability.c
KUKoLex/data/kmat/_exploit/fst_probability_io.c
KUKoLex/data/kmat/_exploit/fstdic.c
KUKoLex/data/kmat/_exploit/fstdic.h
KUKoLex/data/kmat/_exploit/fstdic_build.c
KUKoLex/data/kmat/_exploit/hsplit.c
KUKoLex/data/kmat/_exploit/hsplit.h
KUKoLex/data/kmat/_exploit/load_double.c
KUKoLex/data/kmat/_exploit/load_double.h
KUKoLex/data/kmat/_exploit/probtool.h
KUKoLex/data/kmat/_exploit/sort_uniq.h
KUKoLex/data/kmat/_exploit/t2b.c
KUKoLex/data/kmat/bin/README.TXT
KUKoLex/data/kmat/bin/kma
KUKoLex/data/kmat/bin/kmat
KUKoLex/data/kmat/bin/kornkrv1.txt
KUKoLex/data/kmat/bin/kornkrv1.txt.out
KUKoLex/data/kmat/bin/test.txt
KUKoLex/data/kmat/bin/test.txt.out
KUKoLex/data/kmat/bin_src/Makefile
KUKoLex/data/kmat/bin_src/kma_run.c
KUKoLex/data/kmat/bin_src/kma_run.o
KUKoLex/data/kmat/bin_src/kmat_run.c
KUKoLex/data/kmat/bin_src/kmat_run.o
KUKoLex/data/kmat/exploit/Makefile
KUKoLex/data/kmat/exploit/b2t.c
KUKoLex/data/kmat/exploit/b2t.o
KUKoLex/data/kmat/exploit/bin2txt.h
KUKoLex/data/kmat/exploit/binio.c
KUKoLex/data/kmat/exploit/binio.h
KUKoLex/data/kmat/exploit/binio.o
KUKoLex/data/kmat/exploit/dafst.c
KUKoLex/data/kmat/exploit/dafst.h
KUKoLex/data/kmat/exploit/dafst.o
KUKoLex/data/kmat/exploit/file2lines.c
KUKoLex/data/kmat/exploit/file2lines.o
KUKoLex/data/kmat/exploit/fst_get_probability.c
KUKoLex/data/kmat/exploit/fst_get_probability.o
kukolex-0.0.7.dist-info/LICENSE
kukolex-0.0.7.dist-info/METADATA
kukolex-0.0.7.dist-info/WHEEL
kukolex-0.0.7.dist-info/top_level.txt
kukolex-0.0.7.dist-info/RECORD
