Metadata-Version: 2.1
Name: kukolex
Version: 0.0.7
Summary: Korean morphological analyzer and tagger.
Home-page: https://github.com/nlpai-lab/KU_KoLex
Author: NLP&AI LAB (Heuiseok Lim, Yuna Hur, Yoonna Jang)
Author-email: nlpai@korea.ac.kr
License: MIT
Keywords: POS morpheme tagger
Platform: UNKNOWN
Classifier: Programming Language :: Python :: 3
Classifier: Programming Language :: Python :: 3.2
Classifier: Programming Language :: Python :: 3.3
Classifier: Programming Language :: Python :: 3.4
Classifier: Programming Language :: Python :: 3.5
Classifier: Programming Language :: Python :: 3.6
Classifier: Programming Language :: Python :: 3.7
Requires-Python: >=3
